pytest_llm_assert/__init__.py
pytest_llm_assert/core.py
pytest_llm_assert/plugin.py
pytest_llm_assert-0.1.0.dist-info/METADATA
pytest_llm_assert-0.1.0.dist-info/WHEEL
pytest_llm_assert-0.1.0.dist-info/entry_points.txt
pytest_llm_assert-0.1.0.dist-info/licenses/LICENSE
pytest_llm_assert-0.1.0.dist-info/RECORD
