Metadata-Version: 2.4
Name: pytest-llm-assert
Version: 0.1.0
Summary: Simple LLM-powered assertions for any pytest test
Project-URL: Homepage, https://github.com/sbroenne/pytest-llm-assert
Project-URL: Documentation, https://github.com/sbroenne/pytest-llm-assert#readme
Project-URL: Repository, https://github.com/sbroenne/pytest-llm-assert
Author: Stefan Broenner
License-Expression: MIT
License-File: LICENSE
Keywords: ai,assertions,llm,pytest,testing
Classifier: Development Status :: 3 - Alpha
Classifier: Framework :: Pytest
Classifier: Intended Audience :: Developers
Classifier: License :: OSI Approved :: MIT License
Classifier: Programming Language :: Python :: 3
Classifier: Programming Language :: Python :: 3.11
Classifier: Programming Language :: Python :: 3.12
Classifier: Programming Language :: Python :: 3.13
Requires-Python: >=3.11
Requires-Dist: azure-identity>=1.15
Requires-Dist: litellm>=1.55
Requires-Dist: pytest>=8.0
Provides-Extra: dev
Requires-Dist: pyright>=1.1; extra == 'dev'
Requires-Dist: pytest>=8.0; extra == 'dev'
Requires-Dist: python-dotenv>=1.0; extra == 'dev'
Requires-Dist: ruff>=0.8; extra == 'dev'
